githubtypr/__init__.py
githubtypr/github.py
githubtypr/main.py
githubtypr/options.py
githubtypr/py.typed
githubtypr/utils.py
githubtypr/cli/__init__.py
githubtypr/cli/repo.py
githubtypr/cli/user.py
githubtypr-0.1.1.dist-info/METADATA
githubtypr-0.1.1.dist-info/WHEEL
githubtypr-0.1.1.dist-info/entry_points.txt
githubtypr-0.1.1.dist-info/RECORD
