Metadata-Version: 2.4
Name: githubtypr
Version: 0.1.1
Summary: GitHub CLI for managing GitHub repositories
Project-URL: Homepage, https://github.com/utkarshg1/githubtypr
Project-URL: Issues, https://github.com/utkarshg1/githubtypr/issues
Author-email: utkarshg1 <gaikwadujg@gmail.com>
Requires-Python: >=3.13
Requires-Dist: jmespath>=1.0.1
Requires-Dist: python-dotenv>=1.1.0
Requires-Dist: requests>=2.32.3
Requires-Dist: typer>=0.15.3
